<?xml version='1.0' encoding='UTF-8'?>
<data>
<info>
  <savetime>12:48:02 22-05-2017</savetime>
  <progress>completed</progress>
</info>

<schema path="./" protocol="file">temporal.schema.xml</schema>

<annotations>
	<entity>
		<id>57@e@NYT19980402.0453@gold</id>
		<span>87,89</span>
		<type>Second-Of-Minute</type>
		<parentsType>Repeating-Interval</parentsType>
		<properties>
			<Value>0</Value>
			<Number></Number>
			<Modifier></Modifier>
		</properties>
	</entity>

	<entity>
		<id>58@e@NYT19980402.0453@gold</id>
		<span>2089,2092</span>
		<type>Time-Zone</type>
		<parentsType>Repeating-Interval</parentsType>
		<properties>
		</properties>
	</entity>

	<entity>
		<id>59@e@NYT19980402.0453@gold</id>
		<span>1301,1306</span>
		<type>Between</type>
		<parentsType>Operator</parentsType>
		<properties>
			<Start-Interval-Type>Link</Start-Interval-Type>
			<Start-Interval>72@e@NYT19980402.0453@gold</Start-Interval>
			<End-Interval-Type>DocTime</End-Interval-Type>
			<End-Interval></End-Interval>
			<Start-Included>Not-Included</Start-Included>
			<End-Included>Not-Included</End-Included>
		</properties>
	</entity>

	<entity>
		<id>60@e@NYT19980402.0453@gold</id>
		<span>34,36</span>
		<type>Minute-Of-Hour</type>
		<parentsType>Repeating-Interval</parentsType>
		<properties>
			<Value>52</Value>
			<Sub-Interval>61@e@NYT19980402.0453@gold</Sub-Interval>
			<Number></Number>
			<Modifier></Modifier>
		</properties>
	</entity>

	<entity>
		<id>61@e@NYT19980402.0453@gold</id>
		<span>37,39</span>
		<type>Second-Of-Minute</type>
		<parentsType>Repeating-Interval</parentsType>
		<properties>
			<Value>0</Value>
			<Number></Number>
			<Modifier></Modifier>
		</properties>
	</entity>

	<entity>
		<id>62@e@NYT19980402.0453@gold</id>
		<span>2085,2087</span>
		<type>Hour-Of-Day</type>
		<parentsType>Repeating-Interval</parentsType>
		<properties>
			<Value>22</Value>
			<AMPM-Of-Day></AMPM-Of-Day>
			<Time-Zone>58@e@NYT19980402.0453@gold</Time-Zone>
			<Sub-Interval>67@e@NYT19980402.0453@gold</Sub-Interval>
			<Number></Number>
			<Modifier></Modifier>
		</properties>
	</entity>

	<entity>
		<id>63@e@NYT19980402.0453@gold</id>
		<span>1983,1990</span>
		<type>Last</type>
		<parentsType>Operator</parentsType>
		<properties>
			<Semantics>Interval-Not-Included</Semantics>
			<Interval-Type>DocTime</Interval-Type>
			<Interval></Interval>
			<Period></Period>
			<Repeating-Interval>64@e@NYT19980402.0453@gold</Repeating-Interval>
		</properties>
	</entity>

	<entity>
		<id>64@e@NYT19980402.0453@gold</id>
		<span>1983,1990</span>
		<type>Day-Of-Week</type>
		<parentsType>Repeating-Interval</parentsType>
		<properties>
			<Type>Tuesday</Type>
			<Sub-Interval></Sub-Interval>
			<Number></Number>
			<Modifier></Modifier>
		</properties>
	</entity>

	<entity>
		<id>65@e@NYT19980402.0453@gold</id>
		<span>479,484</span>
		<type>Period</type>
		<parentsType>Duration</parentsType>
		<properties>
			<Type>Years</Type>
			<Number>73@e@NYT19980402.0453@gold</Number>
			<Modifier></Modifier>
		</properties>
	</entity>

	<entity>
		<id>66@e@NYT19980402.0453@gold</id>
		<span>84,86</span>
		<type>Minute-Of-Hour</type>
		<parentsType>Repeating-Interval</parentsType>
		<properties>
			<Value>52</Value>
			<Sub-Interval>57@e@NYT19980402.0453@gold</Sub-Interval>
			<Number></Number>
			<Modifier></Modifier>
		</properties>
	</entity>

	<entity>
		<id>67@e@NYT19980402.0453@gold</id>
		<span>2087,2089</span>
		<type>Minute-Of-Hour</type>
		<parentsType>Repeating-Interval</parentsType>
		<properties>
			<Value>52</Value>
			<Sub-Interval></Sub-Interval>
			<Number></Number>
			<Modifier></Modifier>
		</properties>
	</entity>

	<entity>
		<id>68@e@NYT19980402.0453@gold</id>
		<span>155,157</span>
		<type>Month-Of-Year</type>
		<parentsType>Repeating-Interval</parentsType>
		<properties>
			<Type>April</Type>
			<Sub-Interval>69@e@NYT19980402.0453@gold</Sub-Interval>
			<Number></Number>
			<Modifier></Modifier>
		</properties>
	</entity>

	<entity>
		<id>69@e@NYT19980402.0453@gold</id>
		<span>158,160</span>
		<type>Day-Of-Month</type>
		<parentsType>Repeating-Interval</parentsType>
		<properties>
			<Value>2</Value>
			<Sub-Interval></Sub-Interval>
			<Number></Number>
			<Modifier></Modifier>
		</properties>
	</entity>

	<entity>
		<id>70@e@NYT19980402.0453@gold</id>
		<span>306,310</span>
		<type>Year</type>
		<parentsType>Interval</parentsType>
		<properties>
			<Value>1998</Value>
			<Sub-Interval></Sub-Interval>
			<Modifier></Modifier>
		</properties>
	</entity>

	<entity>
		<id>71@e@NYT19980402.0453@gold</id>
		<span>415,423</span>
		<type>Day-Of-Week</type>
		<parentsType>Repeating-Interval</parentsType>
		<properties>
			<Type>Thursday</Type>
			<Sub-Interval></Sub-Interval>
			<Number></Number>
			<Modifier></Modifier>
		</properties>
	</entity>

	<entity>
		<id>72@e@NYT19980402.0453@gold</id>
		<span>1307,1311</span>
		<type>Year</type>
		<parentsType>Interval</parentsType>
		<properties>
			<Value>1993</Value>
			<Sub-Interval></Sub-Interval>
			<Modifier></Modifier>
		</properties>
	</entity>

	<entity>
		<id>73@e@NYT19980402.0453@gold</id>
		<span>474,478</span>
		<type>Number</type>
		<parentsType>Other</parentsType>
		<properties>
			<Value>5</Value>
		</properties>
	</entity>

	<entity>
		<id>74@e@NYT19980402.0453@gold</id>
		<span>1141,1145</span>
		<type>Calendar-Interval</type>
		<parentsType>Repeating-Interval</parentsType>
		<properties>
			<Type>Year</Type>
			<Number></Number>
			<Modifier></Modifier>
		</properties>
	</entity>

	<entity>
		<id>75@e@NYT19980402.0453@gold</id>
		<span>81,83</span>
		<type>Hour-Of-Day</type>
		<parentsType>Repeating-Interval</parentsType>
		<properties>
			<Value>22</Value>
			<AMPM-Of-Day></AMPM-Of-Day>
			<Time-Zone></Time-Zone>
			<Sub-Interval>66@e@NYT19980402.0453@gold</Sub-Interval>
			<Number></Number>
			<Modifier></Modifier>
		</properties>
	</entity>

	<entity>
		<id>76@e@NYT19980402.0453@gold</id>
		<span>31,33</span>
		<type>Hour-Of-Day</type>
		<parentsType>Repeating-Interval</parentsType>
		<properties>
			<Value>22</Value>
			<AMPM-Of-Day></AMPM-Of-Day>
			<Time-Zone></Time-Zone>
			<Sub-Interval>60@e@NYT19980402.0453@gold</Sub-Interval>
			<Number></Number>
			<Modifier></Modifier>
		</properties>
	</entity>

	<entity>
		<id>77@e@NYT19980402.0453@gold</id>
		<span>469,473</span>
		<type>Last</type>
		<parentsType>Operator</parentsType>
		<properties>
			<Semantics>Interval-Not-Included</Semantics>
			<Interval-Type>DocTime</Interval-Type>
			<Interval></Interval>
			<Period>65@e@NYT19980402.0453@gold</Period>
			<Repeating-Interval></Repeating-Interval>
		</properties>
	</entity>

	<entity>
		<id>78@e@NYT19980402.0453@gold</id>
		<span>1136,1140</span>
		<type>Last</type>
		<parentsType>Operator</parentsType>
		<properties>
			<Semantics>Interval-Not-Included</Semantics>
			<Interval-Type>DocTime</Interval-Type>
			<Interval></Interval>
			<Period></Period>
			<Repeating-Interval>74@e@NYT19980402.0453@gold</Repeating-Interval>
		</properties>
	</entity>

	<entity>
		<id>79@e@NYT19980402.0453@gold</id>
		<span>903,909</span>
		<type>Last</type>
		<parentsType>Operator</parentsType>
		<properties>
			<Semantics>Interval-Not-Included</Semantics>
			<Interval-Type>DocTime</Interval-Type>
			<Interval></Interval>
			<Period>87@e@NYT19980402.0453@gold</Period>
			<Repeating-Interval></Repeating-Interval>
		</properties>
	</entity>

	<entity>
		<id>80@e@NYT19980402.0453@gold</id>
		<span>23,25</span>
		<type>Day-Of-Month</type>
		<parentsType>Repeating-Interval</parentsType>
		<properties>
			<Value>2</Value>
			<Sub-Interval>76@e@NYT19980402.0453@gold</Sub-Interval>
			<Number></Number>
			<Modifier></Modifier>
		</properties>
	</entity>

	<entity>
		<id>81@e@NYT19980402.0453@gold</id>
		<span>73,75</span>
		<type>Day-Of-Month</type>
		<parentsType>Repeating-Interval</parentsType>
		<properties>
			<Value>2</Value>
			<Sub-Interval>75@e@NYT19980402.0453@gold</Sub-Interval>
			<Number></Number>
			<Modifier></Modifier>
		</properties>
	</entity>

	<entity>
		<id>82@e@NYT19980402.0453@gold</id>
		<span>2076,2078</span>
		<type>Month-Of-Year</type>
		<parentsType>Repeating-Interval</parentsType>
		<properties>
			<Type>April</Type>
			<Sub-Interval>83@e@NYT19980402.0453@gold</Sub-Interval>
			<Number></Number>
			<Modifier></Modifier>
		</properties>
	</entity>

	<entity>
		<id>83@e@NYT19980402.0453@gold</id>
		<span>2079,2081</span>
		<type>Day-Of-Month</type>
		<parentsType>Repeating-Interval</parentsType>
		<properties>
			<Value>2</Value>
			<Sub-Interval>62@e@NYT19980402.0453@gold</Sub-Interval>
			<Number></Number>
			<Modifier></Modifier>
		</properties>
	</entity>

	<entity>
		<id>84@e@NYT19980402.0453@gold</id>
		<span>2082,2084</span>
		<type>Two-Digit-Year</type>
		<parentsType>Operator</parentsType>
		<properties>
			<Interval-Type>DocTime</Interval-Type>
			<Interval></Interval>
			<Value>98</Value>
			<Sub-Interval>82@e@NYT19980402.0453@gold</Sub-Interval>
		</properties>
	</entity>

	<entity>
		<id>85@e@NYT19980402.0453@gold</id>
		<span>70,72</span>
		<type>Month-Of-Year</type>
		<parentsType>Repeating-Interval</parentsType>
		<properties>
			<Type>April</Type>
			<Sub-Interval>81@e@NYT19980402.0453@gold</Sub-Interval>
			<Number></Number>
			<Modifier></Modifier>
		</properties>
	</entity>

	<entity>
		<id>86@e@NYT19980402.0453@gold</id>
		<span>20,22</span>
		<type>Month-Of-Year</type>
		<parentsType>Repeating-Interval</parentsType>
		<properties>
			<Type>April</Type>
			<Sub-Interval>80@e@NYT19980402.0453@gold</Sub-Interval>
			<Number></Number>
			<Modifier></Modifier>
		</properties>
	</entity>

	<entity>
		<id>87@e@NYT19980402.0453@gold</id>
		<span>910,916</span>
		<type>Period</type>
		<parentsType>Duration</parentsType>
		<properties>
			<Type>Years</Type>
			<Number></Number>
			<Modifier></Modifier>
		</properties>
	</entity>

	<entity>
		<id>88@e@NYT19980402.0453@gold</id>
		<span>76,80</span>
		<type>Year</type>
		<parentsType>Interval</parentsType>
		<properties>
			<Value>1998</Value>
			<Sub-Interval>85@e@NYT19980402.0453@gold</Sub-Interval>
			<Modifier></Modifier>
		</properties>
	</entity>

	<entity>
		<id>89@e@NYT19980402.0453@gold</id>
		<span>26,30</span>
		<type>Year</type>
		<parentsType>Interval</parentsType>
		<properties>
			<Value>1998</Value>
			<Sub-Interval>86@e@NYT19980402.0453@gold</Sub-Interval>
			<Modifier></Modifier>
		</properties>
	</entity>

	<entity>
		<id>90@e@NYT19980402.0453@gold</id>
		<span>415,423</span>
		<type>Last</type>
		<parentsType>Operator</parentsType>
		<properties>
			<Semantics>Interval-Included</Semantics>
			<Interval-Type>DocTime</Interval-Type>
			<Interval></Interval>
			<Period></Period>
			<Repeating-Interval>71@e@NYT19980402.0453@gold</Repeating-Interval>
		</properties>
	</entity>

</annotations>

</data>